LICENSE.TXT
MANIFEST.in
setup.py
culinbasiccalculator.egg-info/PKG-INFO
culinbasiccalculator.egg-info/SOURCES.txt
culinbasiccalculator.egg-info/dependency_links.txt
culinbasiccalculator.egg-info/top_level.txt
culinbsaiccalculator.egg-info/SOURCES.txt
culinbsaiccalculator.egg-info/dependency_links.txt
culinbsaiccalculator.egg-info/top_level.txt
pythoncalculatorlibrary/__init__.py